warp/__init__.py
warp/create_domain.py
warp/resolve.py
warp/servers.py
warp/set_ip.py
warp/host/__init__.py
warp/host/host.py
warp_python-1.3.2.dist-info/licenses/LICENSE
warp_python-1.3.2.dist-info/METADATA
warp_python-1.3.2.dist-info/WHEEL
warp_python-1.3.2.dist-info/top_level.txt
warp_python-1.3.2.dist-info/RECORD
