Metadata-Version: 2.4
Name: warp-python
Version: 1.3.2
Summary: A python module for WARP
Home-page: https://github.com/warp-project/warp-python
Author: warp-project, Ryan_shamu
Author-email: tcc@thecommcraft.de, ryanshamu418@gmail.com
Keywords: warp
Classifier: Development Status :: 4 - Beta
Classifier: Intended Audience :: Developers
Classifier: License :: OSI Approved :: MIT License
Classifier: Programming Language :: Python :: 3.6
Classifier: Programming Language :: Python :: 3.7
Classifier: Programming Language :: Python :: 3.8
Classifier: Programming Language :: Python :: 3.9
Requires-Python: >=3.8
License-File: LICENSE
Requires-Dist: requests
Requires-Dist: Flask
Dynamic: author
Dynamic: author-email
Dynamic: classifier
Dynamic: description
Dynamic: description-content-type
Dynamic: home-page
Dynamic: keywords
Dynamic: license-file
Dynamic: requires-dist
Dynamic: requires-python
Dynamic: summary
